openapi_to_django/__init__.py
openapi_to_django/command_line.py
openapi_to_django/exceptions.py
openapi_to_django/openapi.py
openapi_to_django/templates/app_template/__init__.py-tpl
openapi_to_django/templates/app_template/admin.py-tpl
openapi_to_django/templates/app_template/apps.py-tpl
openapi_to_django/templates/app_template/migrations/__init__.py-tpl
openapi_to_django/templates/app_template/models.py-tpl
openapi_to_django/templates/app_template/tests.py-tpl
openapi_to_django/templates/project_template/manage.py-tpl
openapi_to_django/templates/project_template/project_name/__init__.py-tpl
openapi_to_django/templates/project_template/project_name/asgi.py-tpl
openapi_to_django/templates/project_template/project_name/settings.py-tpl
openapi_to_django/templates/project_template/project_name/wsgi.py-tpl
openapi_to_django/templates/urls.py-tpl
openapi_to_django/templates/views.py-tpl
openapi_to_django/urls.py
openapi_to_django/utils.py
openapi_to_django/views.py
openapi_to_django-0.1.0.dist-info/LICENSE.txt
openapi_to_django-0.1.0.dist-info/LICENSES/LICENSE.txt
openapi_to_django-0.1.0.dist-info/LICENSES/LICENSE_DJANGO.txt
openapi_to_django-0.1.0.dist-info/METADATA
openapi_to_django-0.1.0.dist-info/WHEEL
openapi_to_django-0.1.0.dist-info/entry_points.txt
openapi_to_django-0.1.0.dist-info/RECORD
