Metadata-Version: 2.3
Name: openapi_to_django
Version: 0.1.0
Summary: Generate Django code from OpenAPI documents.
License: MIT
Keywords: django,openapi
Author: jaytik1
Requires-Python: >=3.11,<4.0
Classifier: Framework :: Django
Classifier: Intended Audience :: Developers
Classifier: License :: OSI Approved :: MIT License
Classifier: Natural Language :: English
Classifier: Programming Language :: Python :: 3
Classifier: Topic :: Software Development :: Code Generators
Requires-Dist: django (>=5.1.7,<6.0.0)
Requires-Dist: openapi-spec-validator (>=0.7.1,<0.8.0)
Requires-Dist: prance (>=25.4.8.0,<26.0.0.0)
Requires-Dist: pytest (>=8.3.5,<9.0.0)
Requires-Dist: pyyaml (>=6.0.2,<7.0.0)
Requires-Dist: types-pyyaml (>=6.0.12.20241230,<7.0.0.0)
Project-URL: Repository, https://github.com/jaytik1/openapi_to_django
